rsl_comm_py/__init__.py
rsl_comm_py/rsl_autodetect.py
rsl_comm_py/rsl_generate_shearwater.py
rsl_comm_py/rsl_generate_um7.py
rsl_comm_py/rsl_generate_um8.py
rsl_comm_py/rsl_generator.py
rsl_comm_py/rsl_spi.py
rsl_comm_py/serve_rsl_autodetect.py
rsl_comm_py/shearwater_broadcast_packets.py
rsl_comm_py/shearwater_registers.py
rsl_comm_py/shearwater_serial.py
rsl_comm_py/shearwater_spi.py
rsl_comm_py/um7_broadcast_packets.py
rsl_comm_py/um7_registers.py
rsl_comm_py/um7_serial.py
rsl_comm_py/um7_spi.py
rsl_comm_py/um8_broadcast_packets.py
rsl_comm_py/um8_registers.py
rsl_comm_py/um8_serial.py
rsl_comm_py/um8_spi.py
rsl_comm_py/examples/__init__.py
rsl_comm_py/examples/example_shearwater_broadcast.py
rsl_comm_py/examples/example_shearwater_broadcast_all_proc.py
rsl_comm_py/examples/example_shearwater_broadcast_all_raw.py
rsl_comm_py/examples/example_shearwater_broadcast_eurler.py
rsl_comm_py/examples/example_shearwater_broadcast_health.py
rsl_comm_py/examples/example_shearwater_change_meas_range.py
rsl_comm_py/examples/example_shearwater_change_quat_rate.py
rsl_comm_py/examples/example_shearwater_commands.py
rsl_comm_py/examples/example_shearwater_cregs.py
rsl_comm_py/examples/example_shearwater_cregs_as_json.py
rsl_comm_py/examples/example_shearwater_cregs_spi.py
rsl_comm_py/examples/example_shearwater_dregs.py
rsl_comm_py/examples/example_shearwater_hidden.py
rsl_comm_py/examples/example_shearwater_hidden_regs_as_json.py
rsl_comm_py/examples/example_shearwater_inclination.py
rsl_comm_py/examples/example_shearwater_spi.py
rsl_comm_py/examples/example_shearwater_spi_rerun.py
rsl_comm_py/examples/example_um7_baud_rate_change.py
rsl_comm_py/examples/example_um7_broadcast.py
rsl_comm_py/examples/example_um7_broadcast_all_proc.py
rsl_comm_py/examples/example_um7_broadcast_all_raw.py
rsl_comm_py/examples/example_um7_broadcast_eurler.py
rsl_comm_py/examples/example_um7_broadcast_health.py
rsl_comm_py/examples/example_um7_broadcast_quat.py
rsl_comm_py-0.1.11.dist-info/LICENSE
rsl_comm_py-0.1.11.dist-info/METADATA
rsl_comm_py-0.1.11.dist-info/WHEEL
rsl_comm_py-0.1.11.dist-info/top_level.txt
rsl_comm_py-0.1.11.dist-info/RECORD
