Metadata-Version: 2.1
Name: rsl-comm-py
Version: 0.1.11
Summary: Redshift Labs Pty Ltd RSL Communication Python Driver
Home-page: https://github.com/RedshiftLabsPtyLtd/rsl_comm_py
Author: Redshift Labs Pty Ltd, Dr. Konstantin Selyunin
Author-email: selyunin.k.v@gmail.com
License: MIT
Platform: UNKNOWN
Classifier: Programming Language :: Python :: 3.9
Classifier: License :: OSI Approved :: MIT License
Classifier: Operating System :: POSIX
Requires: pyserial
Requires-Dist: pyserial
